django_providerkit-0.1.1.dist-info/licenses/LICENSE
djproviderkit/__init__.py
djproviderkit/managers.py
djproviderkit/urls.py
djproviderkit/admin/__init__.py
djproviderkit/admin/provider.py
djproviderkit/admin/service.py
djproviderkit/models/__init__.py
djproviderkit/models/provider.py
djproviderkit/models/service.py
djproviderkit/views/__init__.py
djproviderkit/views/provider.py
django_providerkit-0.1.1.dist-info/METADATA
django_providerkit-0.1.1.dist-info/WHEEL
django_providerkit-0.1.1.dist-info/top_level.txt
django_providerkit-0.1.1.dist-info/RECORD
