Metadata-Version: 2.4
Name: django-providerkit
Version: 0.1.1
Summary: Django integration for ProviderKit. Provides Django admin integration and utilities for managing providers in Django applications.
Author-email: Hicinformatic <hicinformatic@gmail.com>
License: MIT
Project-URL: Homepage, https://github.com/hicinformatic/django-providerkit
Project-URL: Repository, https://github.com/hicinformatic/django-providerkit
Project-URL: Documentation, https://github.com/hicinformatic/django-providerkit#readme
Project-URL: Issues, https://github.com/hicinformatic/django-providerkit/issues
Keywords: django,provider,service-provider,multi-provider,provider-management,django-admin,python
Classifier: Development Status :: 4 - Beta
Classifier: Intended Audience :: Developers
Classifier: Framework :: Django
Classifier: Framework :: Django :: 3.2
Classifier: Framework :: Django :: 4.0
Classifier: Framework :: Django :: 4.1
Classifier: Framework :: Django :: 4.2
Classifier: Framework :: Django :: 5.0
Classifier: Programming Language :: Python :: 3
Classifier: Programming Language :: Python :: 3.10
Classifier: Programming Language :: Python :: 3.11
Classifier: Programming Language :: Python :: 3.12
Classifier: Topic :: Software Development :: Libraries :: Python Modules
Classifier: Topic :: Internet :: WWW/HTTP :: Dynamic Content
Requires-Python: >=3.10
License-File: LICENSE
Requires-Dist: Django>=3.2
Requires-Dist: providerkit>=0.2.0
Provides-Extra: dev
Requires-Dist: pytest>=8.3; extra == "dev"
Requires-Dist: pytest-django>=4.5; extra == "dev"
Requires-Dist: ruff>=0.5; extra == "dev"
Requires-Dist: mypy>=1.0; extra == "dev"
Requires-Dist: django-stubs>=5.0.0; extra == "dev"
Requires-Dist: python-dotenv>=1.0; extra == "dev"
Provides-Extra: lint
Requires-Dist: ruff>=0.5.0; extra == "lint"
Requires-Dist: mypy>=1.0.0; extra == "lint"
Provides-Extra: quality
Requires-Dist: radon>=6.0.0; extra == "quality"
Requires-Dist: vulture>=2.0.0; extra == "quality"
Requires-Dist: autoflake>=2.0.0; extra == "quality"
Provides-Extra: security
Requires-Dist: bandit>=1.7.0; extra == "security"
Requires-Dist: safety>=3.0.0; extra == "security"
Requires-Dist: pip-audit>=2.7.0; extra == "security"
Dynamic: license-file
